[
    {
        "Error": "Message: \n",
        "Index": "4",
        "failed_requests": "pidfile"
    },
    {
        "Error": "Message: \n",
        "Index": "57",
        "failed_requests": "racc"
    },
    {
        "Error": "Message: \n",
        "Index": "63",
        "failed_requests": "readline"
    },
    {
        "Error": "Message: \n",
        "Index": "66",
        "failed_requests": "readline-sys"
    },
    {
        "Error": "Message: \n",
        "Index": "74",
        "failed_requests": "rest_easy"
    },
    {
        "Error": "Message: \n",
        "Index": "75",
        "failed_requests": "rethinkdb"
    },
    {
        "Error": "Message: \n",
        "Index": "81",
        "failed_requests": "rope"
    },
    {
        "Error": "Message: \n",
        "Index": "83",
        "failed_requests": "route-recognizer"
    },
    {
        "Error": "Message: \n",
        "Index": "85",
        "failed_requests": "rsmtp"
    },
    {
        "Error": "Message: \n",
        "Index": "87",
        "failed_requests": "rum"
    },
    {
        "Error": "Message: \n",
        "Index": "88",
        "failed_requests": "rush"
    },
    {
        "Error": "Message: \n",
        "Index": "94",
        "failed_requests": "rust-bindgen"
    },
    {
        "Error": "Message: \n",
        "Index": "97",
        "failed_requests": "rustclient"
    },
    {
        "Error": "Message: \n",
        "Index": "101",
        "failed_requests": "rust-forms"
    },
    {
        "Error": "Message: \n",
        "Index": "116",
        "failed_requests": "rust-xml"
    },
    {
        "Error": "Message: \n",
        "Index": "117",
        "failed_requests": "rusty"
    },
    {
        "Error": "Message: \n",
        "Index": "121",
        "failed_requests": "schuppe"
    },
    {
        "Error": "Message: \n",
        "Index": "141",
        "failed_requests": "servo"
    },
    {
        "Error": "Message: \n",
        "Index": "144",
        "failed_requests": "sha1-hasher"
    },
    {
        "Error": "Message: \n",
        "Index": "0",
        "failed_requests": "servo"
    },
    {
        "Error": "Message: \n",
        "Index": "3",
        "failed_requests": "sha1-hasher"
    },
    {
        "Error": "Message: \n",
        "Index": "11",
        "failed_requests": "simple-cgi"
    },
    {
        "Error": "Message: \n",
        "Index": "46",
        "failed_requests": "streaming"
    },
    {
        "Error": "Message: \n",
        "Index": "69",
        "failed_requests": "tempan"
    },
    {
        "Error": "Message: \n",
        "Index": "91",
        "failed_requests": "truthtable"
    },
    {
        "Error": "Message: \n",
        "Index": "95",
        "failed_requests": "tweetust_macros"
    }
]